material_color_utilities-0.2.6.dist-info/WHEEL
material_color_utilities-0.2.6.dist-info/METADATA
material_color_utilities-0.2.6.dist-info/RECORD
material_color_utilities-0.2.6.dist-info/licenses/LICENSE
material_color_utilities.libs/libstdc++-0530927c.so.6.0.32
material_color_utilities.libs/libgcc_s-1257a076.so.1
material_color_utilities/_core.cpython-313-i386-linux-musl.so
material_color_utilities/_core.py
material_color_utilities/image_utils.py
material_color_utilities/py.typed
material_color_utilities/__init__.py
