Metadata-Version: 2.1
Name: material-color-utilities
Version: 0.2.6
Summary: Theme color library for Material You.
Author-Email: Ruurd Bijlsma <ruurd@bijlsma.dev>
License: 
Project-URL: Homepage, https://github.com/RuurdBijlsma/material-color-utilities
Project-URL: Repository, https://github.com/RuurdBijlsma/material-color-utilities
Project-URL: Documentation, https://github.com/RuurdBijlsma/material-color-utilities/blob/main/README.md
Requires-Python: >=3.11
Requires-Dist: numpy>=2.2.6
Requires-Dist: pillow>=11.1.0
